tkcalendar/__init__.py
tkcalendar/__main__.py
tkcalendar/calendar_.py
tkcalendar/dateentry.py
tkcalendar/tooltip.py
tkcalendar-1.6.0.dist-info/LICENSE.txt
tkcalendar-1.6.0.dist-info/METADATA
tkcalendar-1.6.0.dist-info/WHEEL
tkcalendar-1.6.0.dist-info/top_level.txt
tkcalendar-1.6.0.dist-info/RECORD
